viking_file/__init__.py
viking_file/api.py
viking_file/classes.py
viking_file/exceptions.py
viking_file/clients/client.py
viking_file/clients/client_async.py
viking_file-1.0.5.dist-info/licenses/LICENSE
viking_file-1.0.5.dist-info/METADATA
viking_file-1.0.5.dist-info/WHEEL
viking_file-1.0.5.dist-info/top_level.txt
viking_file-1.0.5.dist-info/RECORD
