Metadata-Version: 2.4
Name: viking-file
Version: 1.0.5
Summary: API Wrapper for ViKiNG FiLE API (https://vikingfile.com)
Author-email: arabianq <a.tevg@ya.ru>
Project-URL: Repository, https://github.com/arabianq/viking-file-python
Project-URL: Documentation, https://github.com/arabianq/viking-file-python
Project-URL: Releases, https://pypi.org/project/viking-file/#history
Keywords: viking-file,vikingfile,api
Classifier: Programming Language :: Python :: 3
Classifier: License :: OSI Approved :: MIT License
Classifier: Operating System :: OS Independent
Requires-Python: >=3.13
License-File: LICENSE
Requires-Dist: aiofiles>=24.1.0
Requires-Dist: aiohttp>=3.12.15
Dynamic: license-file
